{ "type":"object",
  "title": "Sepa Credit Transfer",
  "name": "sepa_credit_transfer",
  "description": "A transfer initiates a transaction e.g get / send money. Depending on its state a transfer can be edited, deleted. If the transfer fails no transaction is created!",
  "properties":{
    "id":{
      "description":"Unique identifier",
      "identity":true,
      "readonly":true,
      "type":"integer"
    },
    "external_uid":{
      "description": "Unique ID of the creator of the transfer",
      "type":"string",
      "required" : true
    },
    "account_id":{
      "description": "Fidor account this transaction belongs to.",
      "required" : true,
      "type":"integer"
    },
    "user_id":{
      "description": "User who initiated the transfer.",
      "readonly":true,
      "type":"integer"
    },
    "transaction_id":{
      "description": "For successful transfers, the reference to the transaction",
      "readonly":true,
      "type":"integer"
    },
    "subject":{
      "description": "Transfer subject (reference)",
      "type":"string",
      "maxLength": 255
    },
    "amount":{
      "description": "The transferred amount in account currency, two decimal places",
      "type":"number",
      "required" : true
    },
    "external_ref":{
      "description": "A random reference you can set e.g to ref your project.",
      "type":"string",
      "maxLength": 255
    },
    "creditor_fidor_id":{
      "description": "Receiving Fidor-Id, if available",
      "type":"integer"
    },
    "creditor_name":{
      "description": "Receiving account holder name",
      "type":"string",
      "maxLength": 70
    },
    "creditor_iban":{
      "description": "Receiver IBAN",
      "type":"string",
      "maxLength": 31
    },
    "creditor_bic":{
      "description": "Receiver BIC / Swift",
      "type":"string",
      "maxLength": 15
    },
    "state":{
      "description": "State of the transfer. in_clearance: Order is currently being processed | processed: Third party system confirmed booking of order | rejected: Order was rejected | error: An error occurred during execution",
      "enum":["in_clearance", "processed", "rejected", "error"],
      "readonly":true,
      "type":"string"
    },
    "created_at":{
      "description": "Creation date-time, never changes.",
      "format":"date-time",
      "readonly":true,
      "type":"string"
    },
    "updated_at":{
      "description": "Last update date-time.",
      "format":"date-time",
      "readonly":true,
      "type":"string"
    }
  },
  "links":[
    { "rel": "self",
      "href": "sepa_credit_transfers/{id}"
    },
    { "rel": "instances",
      "href": "sepa_credit_transfers",
      "properties" : {
        "filter[account_ids]":{
          "title" : "Find transfers belonging to the given account ids. Single id or multiple ids comma-separated.",
          "format":"date",
          "type":"string"
        },
        "filter[created_at_from]":{
          "title" : "Creation date filter from >= date",
          "format":"date",
          "type":"string"
        },
        "filter[created_at_to]":{
          "title" : "Creation date filter to <= date",
          "format":"date",
          "type":"string"
        },
        "filter[states]":{
          "title" : "Filter by single or multiple csv delimited states",
          "enum":["in_clearance", "processed", "rejected", "error"],
          "type":"string"
        },
        "filter[external_ref]":{
          "title" : "Match full external reference",
          "type":"string"
        },
        "page":{
          "title" : "Page",
          "description": "In paginated results set the page to look for",
          "type":"number"
        },
        "per_page":{
          "title" : "Per page",
          "description": "Results per page. Default is 10, max is 100",
          "type":"number"
        },
        "sort":{
          "title" : "Sort",
          "enum":["ASC","DESC"],
          "description": "Sort the results in ASC or DESC",
          "type": "string"
        }
      }
    },
    { "rel": "destroy",
      "href": "sepa_credit_transfers/{id}",
      "method": "DELETE"
    },
    { "rel": "update",
      "href": "sepa_credit_transfers/{id}",
      "method": "PUT"
    },
    { "rel": "create",
      "href": "sepa_credit_transfers",
      "method": "POST"
    },
    { "rel": "transaction",
      "href": "sepa_credit_transfers/{id}/transaction"
    }
  ]
}
